core/__init__.py
core/__version__.py
core/guid.py
new_guid-1.1.0.dist-info/METADATA
new_guid-1.1.0.dist-info/RECORD
new_guid-1.1.0.dist-info/WHEEL
new_guid-1.1.0.dist-info/entry_points.txt
new_guid-1.1.0.dist-info/top_level.txt
